veintiuno/__init__.py
veintiuno/entorno21.py
veintiuno-0.1.5.dist-info/LICENSE
veintiuno-0.1.5.dist-info/METADATA
veintiuno-0.1.5.dist-info/WHEEL
veintiuno-0.1.5.dist-info/top_level.txt
veintiuno-0.1.5.dist-info/RECORD
