Metadata-Version: 2.1
Name: veintiuno
Version: 0.1.5
Summary: A simple package for create and interact a simple BlackJack environment.
Author: Luis Enrique Quispe Paredes (lequispep@gmail.com)
Author-email: lequispep@gmail.com
License: MIT
License-File: LICENSE
